Kekik_fastapi_cache/__init__.py
Kekik_fastapi_cache/coder.py
Kekik_fastapi_cache/decorator.py
Kekik_fastapi_cache/key_builder.py
Kekik_fastapi_cache/backends/__init__.py
Kekik_fastapi_cache/backends/inmemory.py
Kekik_fastapi_cache/backends/memcached.py
Kekik_fastapi_cache-0.2.4.dist-info/METADATA
Kekik_fastapi_cache-0.2.4.dist-info/WHEEL
Kekik_fastapi_cache-0.2.4.dist-info/top_level.txt
Kekik_fastapi_cache-0.2.4.dist-info/RECORD
