Metadata-Version: 2.1
Name: Kekik_fastapi_cache
Version: 0.2.4
Summary: Kekik FastAPI Cache
Home-page: https://github.com/keyiflerolsun/Kekik_fastapi_cache
Author: keyiflerolsun
Author-email: keyiflerolsun@gmail.com
License: GPLv3+
Keywords: Kekik_fastapi_cache,KekikAkademi,keyiflerolsun
Classifier: Development Status :: 5 - Production/Stable
Classifier: License :: OSI Approved :: GNU General Public License v3 or later (GPLv3+)
Classifier: Programming Language :: Python :: 3
Requires-Python: >=3.10
Requires-Dist: setuptools
Requires-Dist: wheel
Requires-Dist: fastapi
Requires-Dist: aiomcache
Requires-Dist: pendulum
Requires-Dist: starlette
